{
  "chapter": 10,
  "verse": 22,
  "order": 394,
  "sanskrit": "वेदानां सामवेदोऽस्मि देवानामस्मि वासवः । इन्द्रियाणां मनश्चास्मि भूतानामस्मि चेतना ॥",
  "hindiTranslation": "मैं वेदोंमें सामवेद हूँ, देवताओंमें इन्द्र हूँ, इन्द्रियोंमें मन हूँ और प्राणियोंकी चेतना हूँ ॥",
  "englishTranslation": "Among the Vedas, I am the Sama Veda; among the radiant beings, I am Indra. Among the senses, I am the mind; among living beings, I am consciousness.",
  "essence": "The divine is not elsewhere; it is the awareness within everything.",
  "speaker": "Krishna",
  "tags": [
    "vibhuti",
    "sama-veda",
    "indra"
  ]
}