{
  "chapter": 8,
  "verse": 18,
  "order": 328,
  "sanskrit": "अव्यक्ताद्व्यक्तयः सर्वाः प्रभवन्त्यहरागमे । रात्र्यागमे प्रलीयन्ते तत्रैवाव्यक्तसंज्ञके ॥",
  "hindiTranslation": "ब्रह्माजीके दिनके आरम्भकालमें अव्यक्त ब्रह्माजीके सूक्ष्मशरीर से सम्पूर्ण प्राणी पैदा होते हैं और ब्रह्माजीकी रातके आरम्भकालमें उसी अव्यक्तमें सम्पूर्ण प्राणी लीन हो जाते हैं ॥",
  "englishTranslation": "At the start of Brahma's day, all beings arise from the unmanifest; at the start of Brahma's night, they dissolve back into that same unmanifest.",
  "essence": "Everything formed returns to the unmanifest in time.",
  "speaker": "Krishna",
  "tags": [
    "avyakta",
    "brahma-day",
    "cosmic-cycle"
  ]
}