{
  "chapter": 8,
  "verse": 21,
  "order": 331,
  "sanskrit": "अव्यक्तोऽक्षर इत्युक्तस्तमाहुः परमां गतिम् । यं प्राप्य न निवर्तन्ते तद्धाम परमं मम ॥",
  "hindiTranslation": "उसीको अव्यक्त और अक्षर कहा गया है और उसीको परमगति कहा गया है तथा जिसको प्राप्त होनेपर जीव फिर लौटकर नहीं आते, वह मेरा परमधाम है ॥",
  "englishTranslation": "That is called the unmanifest and the imperishable. It is the highest goal. Having reached it, one does not return. It is my supreme abode.",
  "essence": "The highest arrival is beyond return.",
  "speaker": "Krishna",
  "tags": [
    "akshara",
    "avyakta",
    "parama-gati"
  ]
}